gentorqkkh/__init__.py
gentorqkkh-0.1.dist-info/METADATA
gentorqkkh-0.1.dist-info/WHEEL
gentorqkkh-0.1.dist-info/top_level.txt
gentorqkkh-0.1.dist-info/RECORD
