Metadata-Version: 2.1
Name: gentorqkkh
Version: 0.1
Summary: A simple Python Json Config Package for minimal projects.
Home-page: UNKNOWN
License: UNKNOWN
Platform: UNKNOWN
Classifier: Programming Language :: Python :: 3
Classifier: License :: OSI Approved :: MIT License
Classifier: Operating System :: OS Independent
Requires: requests
Requires: pyperclip
Requires-Python: >=3.6
